{
  "kind": "collectionType",
  "collectionName": "sponsors",
  "info": {
    "singularName": "sponsor",
    "pluralName": "sponsors",
    "displayName": "Sponsors"
  },
  "options": {
    "draftAndPublish": false
  },
  "pluginOptions": {},
  "attributes": {
    "name": {
      "type": "string",
      "required": true
    },
    "biography": {
      "type": "text"
    },
    "icon": {
      "type": "media",
      "multiple": false,
      "required": true,
      "allowedTypes": [
        "images"
      ]
    },
    "description": {
      "type": "string"
    },
    "posts": {
      "type": "relation",
      "relation": "manyToMany",
      "target": "api::post.post",
      "mappedBy": "sponsors"
    }
  }
}
